oxfordcanvastools/__init__.py
oxfordcanvastools/canvas_api.py
oxfordcanvastools-1.1.dist-info/LICENSE
oxfordcanvastools-1.1.dist-info/METADATA
oxfordcanvastools-1.1.dist-info/WHEEL
oxfordcanvastools-1.1.dist-info/top_level.txt
oxfordcanvastools-1.1.dist-info/RECORD
