Metadata-Version: 2.1
Name: oxfordcanvastools
Version: 1.1
Summary: A minimal set of tools for interacting with the Canvas API at Oxford
Home-page: https://github.com/SABS-R3/oxfordcanvastools
Maintainer: Fergus Cooper
Maintainer-email: fergus.cooper@cs.ox.ac.uk
License: MIT license
Platform: UNKNOWN
Requires-Python: >=3.6
Requires-Dist: requests
